{
  "db_name": "PostgreSQL",
  "query": "INSERT INTO sessions DEFAULT VALUES RETURNING session_id, updated_at, created_at",
  "describe": {
    "columns": [
      {
        "ordinal": 0,
        "name": "session_id",
        "type_info": "Uuid"
      },
      {
        "ordinal": 1,
        "name": "updated_at",
        "type_info": "Timestamptz"
      },
      {
        "ordinal": 2,
        "name": "created_at",
        "type_info": "Timestamptz"
      }
    ],
    "parameters": {
      "Left": []
    },
    "nullable": [
      false,
      false,
      false
    ]
  },
  "hash": "f298a559440648025fb786a84f97701869817edfe1f59935e8f1d496525fa23c"
}
